notifyme.py
notifyme-0.1.3.dist-info/DESCRIPTION.rst
notifyme-0.1.3.dist-info/METADATA
notifyme-0.1.3.dist-info/RECORD
notifyme-0.1.3.dist-info/WHEEL
notifyme-0.1.3.dist-info/entry_points.txt
notifyme-0.1.3.dist-info/metadata.json
notifyme-0.1.3.dist-info/top_level.txt
