Metadata-Version: 2.0
Name: notifyme
Version: 0.1.3
Summary: Email notifications on task completion
Home-page: https://github.com/brenns10/notifyme
Author: Stephen Brennan
Author-email: stephen@stephen-brennan.com
License: Revised BSD
Keywords: notify notifications email
Platform: UNKNOWN
Classifier: Development Status :: 3 - Alpha
Classifier: License :: OSI Approved :: BSD License
Classifier: Intended Audience :: Science/Research
Classifier: Intended Audience :: Developers
Classifier: Environment :: Console
Classifier: Natural Language :: English
Classifier: Programming Language :: Python :: 3 :: Only
Classifier: Topic :: Communications :: Email :: Email Clients (MUA)
Classifier: Topic :: Utilities
